<?xml version="1.0" encoding="UTF-8"?>
<odoo>
    <data>

        <record model="ir.ui.view" id="view_classroom_form">
            <field name="name">classroom.form</field>
            <field name="model">classroom</field>
            <field name="arch" type="xml">
                <form>
                    <sheet>
                        <group>
                            <group>
                                <field name="name"/>

                                <field name="dob"/>
                                <field name="age"/>
                            </group>
                            <group string="Address">
                                <div class="o_address_format">
                                    <div class="o_address_street">
                                        <div class="o_address_format_div">
                                            <field name="address_street" placeholder="Street..."/>
                                        </div>
                                        <div class="o_address_format_div">
                                            <field name="address_street2" placeholder="Street 2..."/>
                                        </div>
                                    </div>
                                    <div class="oe_inline o_address_format_div o_address_inline_fields">
                                        <div class="o_address_inline_field">
                                            <field name="country_id" placeholder="Country"/>
                                        </div>
                                        <div class="o_address_inline_field">
                                            <field name="state_id" placeholder="State"/>
                                        </div>
                                        <div class="o_address_inline_field o_address_zip">
                                            <field name="address_pincode" placeholder="ZIP"/>
                                        </div>
                                    </div>
                                </div>
                            </group>


                            <!--                            <form>-->


                            <!--                          -->

                            <!--                            </form>-->


                            <!--                            <group string="Address">-->
                            <!--                                <div class="o_group">-->
                            <!--                                    <div class="o_group_col_12">-->
                            <!--                                        <field name="address_street" placeholder="Street" /> - -->
                            <!--                                    </div>-->
                            <!--                                    <div class="o_group_col_6">-->
                            <!--                                        <field name="address_street2" placeholder="Street 2"/> - -->
                            <!--                                        <field name="address_city" placeholder="City"/>-->
                            <!--                                    </div>-->
                            <!--                                    <div class="o_group_col_3">-->

                            <!--                                        <field name="address_pincode" placeholder="pincode"/> - -->
                            <!--                                        <field name="address_district" placeholder="District" default="Kerala"/>- -->
                            <!--                                        <field name="address_country" placeholder="Country" default="India"/>-->
                            <!--                                    </div>-->
                            <!--                                </div>-->
                            <!--                            </group>-->
                            <!--                            <group string="address">-->


                            <!--                                <div class="o_address_format">-->
                            <!--                                    <field name="address_street" placeholder="Street..." class="o_address_street"-->
                            <!--                                    />-->
                            <!--                                    <field name="address_street2" placeholder="Street 2..." class="o_address_street"-->
                            <!--                                    />-->
                            <!--                                    <div class="oe_inline">-->
                            <!--                                        <field name="address_city" placeholder="City" class="o_address_city"-->
                            <!--                                        />-->
                            <!--                                        <field name="address_district" class="o_address_state" placeholder="State"-->

                            <!--                                        />-->
                            <!--                                        <field name="address_pincode" placeholder="ZIP" class="o_address_zip"-->
                            <!--                                        />-->
                            <!--                                    </div>-->
                            <!--                                   <field name="address_country" placeholder="country" />-->

                            <!--                                </div>-->


                            <!--                            </group>-->
                            <!--                            &lt;!&ndash;                                                        <group string="Address">&ndash;&gt;-->
                            <!--                                                            <div class="oe_inline">-->
                            <!--                                                                <field name="address_street"  placeholder="Enter Your street"/> /-->
                            <!--                                                                <field name="address_street2" placeholder="streer 1 "/>-->
                            <!--                                                            </div>-->
                            <!--                                                            <div class="oe_inline">-->
                            <!--                                                                <field name="address_city"  placeholder="city" col="3"/> /-->
                            <!--                                                                <field name="address_district"  placeholder="district" col="3"/> /-->
                            <!--                                                                <field name="address_pincode"  placeholder="pincode" col="3"/>-->
                            <!--                                                            </div>-->
                            <!--                                                            <field name="address_country"  placeholder="country" />-->
                            <!--                                                        </group>-->


                        </group>


                        <notebook>

                            <page string="Marklist">
                                <field name="marklist">
                                    <tree>
                                        <field name="exam_name"/>
                                        <field name="subject1"/>
                                        <field name="subject2"/>
                                        <field name="subject3"/>
                                        <field name="subject4"/>

                                        <field name="average" readonly="1"/>
                                        <field name="total" readonly="1"/>

                                    </tree>

                                </field>
                            </page>
                        </notebook>
                        <div>

                            <div style="text-align: right; color: #ff5733; font-weight: bold;">
                                Total Marks:
                                <field name="total_marks_all" readonly="1"/>
                            </div>
                        </div>
                    </sheet>
                </form>
            </field>
        </record>


        <record model="ir.ui.view" id="view_classroom_tree">
            <field name="name">classroom.tree,form</field>
            <field name="model">classroom</field>
            <field name="arch" type="xml">
                <tree>
                    <field name="name"/>
                    <field name="dob"/>
                    <field name="age"/>
                </tree>
            </field>
        </record>


        <record model="ir.ui.view" id="view_marklist_tree">
            <field name="name">marklist.tree</field>
            <field name="model">marklist</field>
            <field name="arch" type="xml">
                <group>
                    <tree>
                        <field name="exam_name"/>
                        <field name="subject1"/>
                        <field name="subject2"/>
                        <field name="subject3"/>
                        <field name="subject4"/>
                        <field name="total"/>
                        <field name="average"/>

                    </tree>
                </group>


            </field>
        </record>


        <record id="action_school_management_classroom" model="ir.actions.act_window">
            <field name="name">student</field>
            <field name="type">ir.actions.act_window</field>
            <field name="res_model">classroom</field>
            <field name="view_mode">tree,form</field>
            <field name="context">{ }</field>
            <field name="help" type="html">
                <p class="o_view_nocontent_smiling_face">
                    Create your firest student
                </p>
            </field>
        </record>
        <menuitem
                id="menu_classroom"
                name="student"
                parent="menu_classroom_master"
                action="action_school_management_classroom"
                sequence="0"/>

    </data>
</odoo>
